tmus/__init__.py
tmus/app.py
tmus/library_cache.py
tmus/music_scanner.py
tmus-0.5.1.dist-info/licenses/LICENSE
tmus-0.5.1.dist-info/METADATA
tmus-0.5.1.dist-info/WHEEL
tmus-0.5.1.dist-info/entry_points.txt
tmus-0.5.1.dist-info/top_level.txt
tmus-0.5.1.dist-info/RECORD
