Metadata-Version: 2.4
Name: tmus
Version: 0.5.1
Summary: Terminal-based music player for organized music directories.
Author-email: Ismail Manjlai <brave.key4637@manjlai.dev>
License: MIT License
Requires-Python: >=3.8
License-File: LICENSE
Requires-Dist: python-vlc
Requires-Dist: windows-curses; platform_system == "Windows"
Dynamic: license-file
Dynamic: requires-python
